{
  "email_config": {
    "provider": "GMX",
    "email_address": "tilohue@gmx.de",
    "app_password": "RG2AS4XLT2BIRPUFWGLR",
    "imap_server": "imap.gmx.net",
    "imap_port": 993,
    "use_ssl": true,
    "folder": "INBOX"
  },
  "scanning": {
    "enabled": true,
    "frequency": "twice_daily",
    "schedule": [
      {
        "time": "08:00",
        "timezone": "Europe/Amsterdam",
        "description": "Morning scan"
      },
      {
        "time": "17:00",
        "timezone": "Europe/Amsterdam",
        "description": "Afternoon scan"
      }
    ]
  },
  "output": {
    "format": "markdown",
    "delivery_method": "email",
    "send_to": "tilohue@gmx.de",
    "subject_prefix": "[Inbox Digest]",
    "include_generic_emails": true,
    "include_actions": true,
    "max_generic_emails": 10,
    "max_action_items": 20
  },
  "filtering": {
    "exclude_senders": [
      "noreply@*",
      "notifications@*",
      "no-reply@*"
    ],
    "priority_keywords": {
      "high": ["URGENT", "ASAP", "TODAY", "CRITICAL", "DRINGEND"],
      "medium": ["IMPORTANT", "this week", "diese woche"],
      "low": ["FYI", "when you can", "wenn du zeit hast"]
    }
  },
  "logging": {
    "enabled": true,
    "log_file": "/var/log/email-skill.log",
    "level": "INFO"
  }
}
